odoo/addons/account_move_line_purchase_info/README.rst
odoo/addons/account_move_line_purchase_info/__init__.py
odoo/addons/account_move_line_purchase_info/__manifest__.py
odoo/addons/account_move_line_purchase_info/hooks.py
odoo/addons/account_move_line_purchase_info/i18n/account_move_line_purchase_info.pot
odoo/addons/account_move_line_purchase_info/i18n/ar.po
odoo/addons/account_move_line_purchase_info/i18n/bg.po
odoo/addons/account_move_line_purchase_info/i18n/bs.po
odoo/addons/account_move_line_purchase_info/i18n/ca.po
odoo/addons/account_move_line_purchase_info/i18n/cs.po
odoo/addons/account_move_line_purchase_info/i18n/de.po
odoo/addons/account_move_line_purchase_info/i18n/el_GR.po
odoo/addons/account_move_line_purchase_info/i18n/en_GB.po
odoo/addons/account_move_line_purchase_info/i18n/es.po
odoo/addons/account_move_line_purchase_info/i18n/es_CR.po
odoo/addons/account_move_line_purchase_info/i18n/es_EC.po
odoo/addons/account_move_line_purchase_info/i18n/es_MX.po
odoo/addons/account_move_line_purchase_info/i18n/et.po
odoo/addons/account_move_line_purchase_info/i18n/fi.po
odoo/addons/account_move_line_purchase_info/i18n/fr.po
odoo/addons/account_move_line_purchase_info/i18n/fr_CA.po
odoo/addons/account_move_line_purchase_info/i18n/fr_CH.po
odoo/addons/account_move_line_purchase_info/i18n/gl.po
odoo/addons/account_move_line_purchase_info/i18n/hr.po
odoo/addons/account_move_line_purchase_info/i18n/hr_HR.po
odoo/addons/account_move_line_purchase_info/i18n/hu.po
odoo/addons/account_move_line_purchase_info/i18n/id.po
odoo/addons/account_move_line_purchase_info/i18n/it.po
odoo/addons/account_move_line_purchase_info/i18n/ja.po
odoo/addons/account_move_line_purchase_info/i18n/lt.po
odoo/addons/account_move_line_purchase_info/i18n/mk.po
odoo/addons/account_move_line_purchase_info/i18n/mn.po
odoo/addons/account_move_line_purchase_info/i18n/nb.po
odoo/addons/account_move_line_purchase_info/i18n/nb_NO.po
odoo/addons/account_move_line_purchase_info/i18n/nl.po
odoo13_addon_account_move_line_purchase_info-13.0.1.1.3.dist-info/METADATA
odoo13_addon_account_move_line_purchase_info-13.0.1.1.3.dist-info/WHEEL
odoo13_addon_account_move_line_purchase_info-13.0.1.1.3.dist-info/top_level.txt
odoo13_addon_account_move_line_purchase_info-13.0.1.1.3.dist-info/RECORD
